[
  {
    "episode": 1,
    "title": "Знакомьтесь, Узумаки Наруто!"
  },
  {
    "episode": 2,
    "title": "Конохамару!"
  },
  {
    "episode": 3,
    "title": "Саске и Сакура: друзья или враги?"
  },
  {
    "episode": 4,
    "title": "Трио! Испытание на выживание"
  },
  {
    "episode": 5,
    "title": "Дисквалифицированы? Заключение Какаши"
  },
  {
    "episode": 6,
    "title": "Важная миссия! Направляемся в Страну Волн"
  },
  {
    "episode": 7,
    "title": "Убийца из тумана"
  },
  {
    "episode": 8,
    "title": "Клятва на боли"
  },
  {
    "episode": 9,
    "title": "Шаринган Какаши"
  },
  {
    "episode": 10,
    "title": "Лес Чакры"
  },
  {
    "episode": 11,
    "title": "Страна, у которой был герой"
  },
  {
    "episode": 12,
    "title": "Решающая битва на мосту! Забуза возвращается!!"
  },
  {
    "episode": 13,
    "title": "Секретная техника Хаку: Ледяные зеркала демона"
  },
  {
    "episode": 14,
    "title": "Умеет поражать: Наруто присоединяется к битве!"
  },
  {
    "episode": 15,
    "title": "Битва при нулевой видимости: Шаринган не поможет"
  },
  {
    "episode": 16,
    "title": "Печать пробуждается"
  },
  {
    "episode": 17,
    "title": "Невинное прошлое: спрятанные чувства"
  },
  {
    "episode": 18,
    "title": "Орудие под названием шиноби"
  },
  {
    "episode": 19,
    "title": "Забуза исчезает в снегу..."
  },
  {
    "episode": 20,
    "title": "Новая глава! Экзамен на звание Чунина"
  },
  {
    "episode": 21,
    "title": "Знакомство! Приехали сильные враги!!"
  },
  {
    "episode": 22,
    "title": "Воодушевлены на 120%! Роковой вызов прямо сейчас!"
  },
  {
    "episode": 23,
    "title": "Победить соперников! Великолепная девятка - все собрались!"
  },
  {
    "episode": 24,
    "title": "Я уже провалил? Невероятно сложный первый экзамен"
  },
  {
    "episode": 25,
    "title": "Это он! Последний десятый вопрос!"
  },
  {
    "episode": 26,
    "title": "Нужно посмотреть! Репортаж перед входом в Лес Смерти! Это школьная газета Конохамару!"
  },
  {
    "episode": 27,
    "title": "Второй экзамен начинается! Все вокруг - враги!"
  },
  {
    "episode": 28,
    "title": "Ешь или будь съеденным! Наруто как приманка"
  },
  {
    "episode": 29,
    "title": "Наруто атакует! Я не собираюсь убегать!"
  },
  {
    "episode": 30,
    "title": "Проснись, Шаринган! Последний ход: Пламя Дракона"
  },
  {
    "episode": 31,
    "title": "Супер большие брови! Я защищу тебя от смерти!!"
  },
  {
    "episode": 32,
    "title": "Сакура цветет! Возвращение решимости"
  },
  {
    "episode": 33,
    "title": "Боевое формирование: Ино-Шика-Чо"
  },
  {
    "episode": 34,
    "title": "Акамару удивлен! Исключительные способности Гаары"
  },
  {
    "episode": 35,
    "title": "Запрещено смотреть! Секрет свитка"
  },
  {
    "episode": 36,
    "title": "Схватка клонов! Главный герой - я!"
  },
  {
    "episode": 37,
    "title": "Второй экзамен завершен! Все здесь, Великолепная Девятка!"
  },
  {
    "episode": 38,
    "title": "Поражение - 50%!? Неожиданная битва!!"
  },
  {
    "episode": 39,
    "title": "Зависть Густобровика! Рождение «Комбо Льва»!"
  },
  {
    "episode": 40,
    "title": "Рискованная ситуация!! Какаши против Орочимару"
  },
  {
    "episode": 41,
    "title": "Соперники встретились! Сердца девчонок серьезно настроены"
  },
  {
    "episode": 42,
    "title": "Лучшая битва, чёрт побери!!"
  },
  {
    "episode": 43,
    "title": "Шикамару поражен!? Битва девушек-ниндзя на поражение"
  },
  {
    "episode": 44,
    "title": "Акамару приходит на помощь!! Кого побьют как собаку?"
  },
  {
    "episode": 45,
    "title": "Хината краснеет! Все широко открыли рты, козырная карта Наруто"
  },
  {
    "episode": 46,
    "title": "Бьякуган идёт в атаку!! Отважная решимость скромной Хинаты!"
  },
  {
    "episode": 47,
    "title": "Перед человеком, которого я обожаю!!"
  },
  {
    "episode": 48,
    "title": "Гаара поражён!! Она твоя! Сила! И взрыв!"
  },
  {
    "episode": 49,
    "title": "Неудачник с горячей кровью! Наконец-то идёт в атаку непревзойденный мастер движения!"
  },
  {
    "episode": 50,
    "title": "Слава Року Ли! Вот таким должен быть мужчина!!"
  },
  {
    "episode": 51,
    "title": "Тень, двигающаяся в темноте. Опасность приближается к Саске!"
  },
  {
    "episode": 52,
    "title": "Эбису возвращается! Я не разрешу бесстыдство!"
  },
  {
    "episode": 53,
    "title": "Встречайте! Появление развратного отшельника!"
  },
  {
    "episode": 54,
    "title": "Школа развратного отшельника! Техника призыва!"
  },
  {
    "episode": 55,
    "title": "Тяжелое предчувствие. Цветок с загаданным желанием"
  },
  {
    "episode": 56,
    "title": "Жизнь или смерть!? Смертельно-опасное обучение!"
  },
  {
    "episode": 57,
    "title": "Летай! Прыгай! Ныряй! Встречайте Жабьего Босса!"
  },
  {
    "episode": 58,
    "title": "Рука зла близка! Больница в опасности"
  },
  {
    "episode": 59,
    "title": "Суперускорение и сокрушительный удар. Начало турнира!"
  },
  {
    "episode": 60,
    "title": "Бьякуган против теневых клонов! Я выиграю!!"
  },
  {
    "episode": 61,
    "title": "Слабых мест нет! Еще одна абсолютная защита"
  },
  {
    "episode": 62,
    "title": "Скрытая сила неудачника!"
  },
  {
    "episode": 63,
    "title": "Дисквалифицирован!? Опасность! Проблемы с расписанием"
  },
  {
    "episode": 64,
    "title": "Красивые облака... И «парень-пофигист»"
  },
  {
    "episode": 65,
    "title": "Столкновение! Взрывающийся Листок и Песок Зла"
  },
  {
    "episode": 66,
    "title": "Человек, вызывающий бурю!! Стиль толстобровика!"
  },
  {
    "episode": 67,
    "title": "Мы опоздали не просто так! Непобедимая техника Чидори!!"
  },
  {
    "episode": 68,
    "title": "«Разрушение деревни Коноха» начинается!"
  },
  {
    "episode": 69,
    "title": "Я ждал этого! Миссия ранга А!"
  },
  {
    "episode": 70,
    "title": "Трус номер один - Это причиняет беспокойство, но я должен сделать это!!"
  },
  {
    "episode": 71,
    "title": "Абсолютно несравненно! Битва уровня Хокаге"
  },
  {
    "episode": 72,
    "title": "Ошибка Хокаге - истинное лицо под маской"
  },
  {
    "episode": 73,
    "title": "Запретная техника мастера! «Демоническая печать»"
  },
  {
    "episode": 74,
    "title": "Невероятно! Истинная сущность Гаары"
  },
  {
    "episode": 75,
    "title": "Переходя за предел... Решение Саске!!"
  },
  {
    "episode": 76,
    "title": "Убийца из лунной ночи"
  },
  {
    "episode": 77,
    "title": "Свет против тьмы в лице Гаары"
  },
  {
    "episode": 78,
    "title": "Взрыв! Книга техник Наруто!!"
  },
  {
    "episode": 79,
    "title": "Шаг за предел! Свет и тьма"
  },
  {
    "episode": 80,
    "title": "Прощай навеки, Третий Хокаге......!!"
  },
  {
    "episode": 81,
    "title": "Возвращение в утреннем тумане"
  },
  {
    "episode": 82,
    "title": "Шаринган против Шарингана"
  },
  {
    "episode": 83,
    "title": "О нет! Джирайя - источник неприятностей женщин и Наруто"
  },
  {
    "episode": 84,
    "title": "Крик Чидори и рёв Саске!"
  },
  {
    "episode": 85,
    "title": "Глупый брат, сила ненависти и злости!"
  },
  {
    "episode": 86,
    "title": "Начало тренировок. Я должен стать сильнее!"
  },
  {
    "episode": 87,
    "title": "Ну давай! Лопни же!"
  },
  {
    "episode": 88,
    "title": "Знак Конохи на налобной повязке"
  },
  {
    "episode": 89,
    "title": "Водная рябь"
  },
  {
    "episode": 90,
    "title": "Взрывной гнев! Ты поплатишься"
  },
  {
    "episode": 91,
    "title": "Наследство Первого Хокаге. Ожерелье, призывающее смерть"
  },
  {
    "episode": 92,
    "title": "Да или нет! Решение Цунаде"
  },
  {
    "episode": 93,
    "title": "Переговоры окончены!!"
  },
  {
    "episode": 94,
    "title": "Атака! Ярость Расенгана"
  },
  {
    "episode": 95,
    "title": "Пятый Хокаге. Битва не на жизнь, а насмерть"
  },
  {
    "episode": 96,
    "title": "Битва легендарной троицы!"
  },
  {
    "episode": 97,
    "title": "Похищение! Приключения Наруто на горячем источнике!"
  },
  {
    "episode": 98,
    "title": "Оставить путь ниндзя! Предупреждение Цунаде"
  },
  {
    "episode": 99,
    "title": "Тот, кто унаследует волю Огня."
  },
  {
    "episode": 100,
    "title": "Клятва учителя и ученика. Настоящий мужчина и путь ниндзя."
  },
  {
    "episode": 101,
    "title": "Пора увидеть! Пора узнать истинное лицо Какаши-сенсея!"
  },
  {
    "episode": 102,
    "title": "Миссия: Помочь старому знакомому в стране Чая!"
  },
  {
    "episode": 103,
    "title": "Гонка продолжается! Неприятности в море!"
  },
  {
    "episode": 104,
    "title": "Беги Идате, беги! Остров Наги ждёт!"
  },
  {
    "episode": 105,
    "title": "Почти у цели! Ревущий гром большой битвы"
  },
  {
    "episode": 106,
    "title": "Успеешь ли ты, Идате?! Финишная прямая!!"
  },
  {
    "episode": 107,
    "title": "Я хочу сразиться с тобой! Столкновение Саске и Наруто!"
  },
  {
    "episode": 108,
    "title": "Невидимый раскол"
  },
  {
    "episode": 109,
    "title": "Приглашение из Звука"
  },
  {
    "episode": 110,
    "title": "Пятеро из Листа плюс 1"
  },
  {
    "episode": 111,
    "title": "Непобедимая команда принимает вызов!"
  },
  {
    "episode": 112,
    "title": "Неожиданная борьба внутри группы!? Отряд Шикамару в опасности!"
  },
  {
    "episode": 113,
    "title": "Полная сила! Пылающий Чоджи!"
  },
  {
    "episode": 114,
    "title": "Прощай, друг...! Даже сейчас, я верю..."
  },
  {
    "episode": 115,
    "title": "Твой противник - я!"
  },
  {
    "episode": 116,
    "title": "360 градусов обзора: слабое место Бьякугана!"
  },
  {
    "episode": 117,
    "title": "Яростная битва между крутыми ребятами!"
  },
  {
    "episode": 118,
    "title": "Возвращайся! Вместилище, время которого ещё не пришло"
  },
  {
    "episode": 119,
    "title": "Ошибка! Новый враг"
  },
  {
    "episode": 120,
    "title": "Рык! Вой! Убойная команда"
  },
  {
    "episode": 121,
    "title": "У каждого своя битва"
  },
  {
    "episode": 122,
    "title": "Подделка! Шикамару, человек, который бьет возродившихся мертвецов!"
  },
  {
    "episode": 123,
    "title": "Появление Зелёного Зверя Листа!"
  },
  {
    "episode": 124,
    "title": "Взрывной Зверь! Бросок, Удар, Прорыв!"
  },
  {
    "episode": 125,
    "title": "Союзники Листа - ниндзя Песка!"
  },
  {
    "episode": 126,
    "title": "Поединок сильнейших! Гаара против Кимимаро!!"
  },
  {
    "episode": 127,
    "title": "Стой, Саске!"
  },
  {
    "episode": 128,
    "title": "Плач был услышан"
  },
  {
    "episode": 129,
    "title": "Итачи и Саске. Жизнь слишком далеко друг от друга"
  },
  {
    "episode": 130,
    "title": "Отец и сын. Треснувшие отношения"
  },
  {
    "episode": 131,
    "title": "Секрет Мангекё Шарингана"
  },
  {
    "episode": 132,
    "title": "Для друга!"
  },
  {
    "episode": 133,
    "title": "Крик, полный слёз! Ты мой друг!!"
  },
  {
    "episode": 134,
    "title": "Конец дождя слез."
  },
  {
    "episode": 135,
    "title": "Несдержанное обещание"
  },
  {
    "episode": 136,
    "title": "Проникаем, расследуем! Вот оно! Сверхзадание класса S"
  },
  {
    "episode": 137,
    "title": "Город преступников. Тень клана Фума"
  },
  {
    "episode": 138,
    "title": "Предательство! Мимолётные желания"
  },
  {
    "episode": 139,
    "title": "Ужас! Убежище Орочимару"
  },
  {
    "episode": 140,
    "title": "Двойной удар. Ловушка Кабуто"
  },
  {
    "episode": 141,
    "title": "Предназначение Сакуры"
  },
  {
    "episode": 142,
    "title": "Троица из тюрьмы строгого режима"
  },
  {
    "episode": 143,
    "title": "Ищи, Тонтон! Мы полагаемся на твой нос"
  },
  {
    "episode": 144,
    "title": "Возрождение команды"
  },
  {
    "episode": 145,
    "title": "Взрыв! Новое построение Ино-Шика-Чо"
  },
  {
    "episode": 146,
    "title": "Утраченные мечты. Тень Орочимару"
  },
  {
    "episode": 147,
    "title": "Противостояние судьбы! Тебе меня не победить"
  },
  {
    "episode": 148,
    "title": "Ревность Акамару к способности поиска! Найти Бикочу!"
  },
  {
    "episode": 149,
    "title": "Где же разница?! Все насекомые выглядят одинаково"
  },
  {
    "episode": 150,
    "title": "Обмануть, чтобы быть обманутым! Великая битва насекомых"
  },
  {
    "episode": 151,
    "title": "Сверкающий Бьякуган! Таков мой путь ниндзя"
  },
  {
    "episode": 152,
    "title": "Похоронный марш для живых"
  },
  {
    "episode": 153,
    "title": "Cердце! Железный кулак Любви"
  },
  {
    "episode": 154,
    "title": "Враг Бьякугана"
  },
  {
    "episode": 155,
    "title": "Жуткая погода"
  },
  {
    "episode": 156,
    "title": "Контратака Райги!"
  },
  {
    "episode": 157,
    "title": "Вперёд! Да поможет нам «живительное» карри!"
  },
  {
    "episode": 158,
    "title": "Все за мной! Испытание потом и слезами"
  },
  {
    "episode": 159,
    "title": "Друг или враг? Охотник за наградой пустыни"
  },
  {
    "episode": 160,
    "title": "Мы возьмём это или это возьмут у нас? OK, битва в храме!"
  },
  {
    "episode": 161,
    "title": "Зелёное животное? Плотоядное животное? Приветствуемое животное?"
  },
  {
    "episode": 162,
    "title": "Белый Нороимуши"
  },
  {
    "episode": 163,
    "title": "Стратег - планы Коумея"
  },
  {
    "episode": 164,
    "title": "Помощник, прибывший слишком поздно"
  },
  {
    "episode": 165,
    "title": "Смерть Наруто"
  },
  {
    "episode": 166,
    "title": "Время, которое остановилось"
  },
  {
    "episode": 167,
    "title": "Когда белые цапли машут своими крыльями"
  },
  {
    "episode": 168,
    "title": "Кипящий котелок! Смешай, размешай и вскипяти!"
  },
  {
    "episode": 169,
    "title": "Воспоминания: потерянная страница"
  },
  {
    "episode": 170,
    "title": "Крушение, закрытая дверь"
  },
  {
    "episode": 171,
    "title": "Крадись: спланированная ловушка"
  },
  {
    "episode": 172,
    "title": "Отчаяние, разбитое сердце"
  },
  {
    "episode": 173,
    "title": "Морское сражение, выпущенная власть"
  },
  {
    "episode": 174,
    "title": "Это невозможно! Знаменитое Искусство ниндзя: Дзюцу Золотого Элемента"
  },
  {
    "episode": 175,
    "title": "Копать здесь! Найти груду золота"
  },
  {
    "episode": 176,
    "title": "Беги и уклоняйся! Преследуй или будь преследуемым"
  },
  {
    "episode": 177,
    "title": "О?! Пожалуйста, господин почтальон"
  },
  {
    "episode": 178,
    "title": "Мальчик, названный «Звездой»"
  },
  {
    "episode": 179,
    "title": "Звезда летнего дня - колыбельная памяти"
  },
  {
    "episode": 180,
    "title": "Секретная Техника Таинственного Павлина"
  },
  {
    "episode": 181,
    "title": "Хошикаге, похороненная правда"
  },
  {
    "episode": 182,
    "title": "Воссоединение: оставшееся время"
  },
  {
    "episode": 183,
    "title": "Звезда, которая сияет ярче"
  },
  {
    "episode": 184,
    "title": "Длинный день Кибы Инузуки"
  },
  {
    "episode": 185,
    "title": "Легенда Листа - Омба и вправду существует"
  },
  {
    "episode": 186,
    "title": "Смеющийся Шино"
  },
  {
    "episode": 187,
    "title": "Открытие Бизнеса!! Перемещающийся Лист"
  },
  {
    "episode": 188,
    "title": "Тайна путешествующих продавцов"
  },
  {
    "episode": 189,
    "title": "Под водой! Бесконечное количество оружия ниндзя"
  },
  {
    "episode": 190,
    "title": "Бьякуган видел это! Мертвая точка пользователя магнита"
  },
  {
    "episode": 191,
    "title": "Смертный приговор, «Облачно, но возможно выглянет Солнце»"
  },
  {
    "episode": 192,
    "title": "Крик Ино! Круглолицый Рай"
  },
  {
    "episode": 193,
    "title": "Додзё Рока Ли"
  },
  {
    "episode": 194,
    "title": "Таинственный проклятый замок призрака"
  },
  {
    "episode": 195,
    "title": "Третий Великий Зверь, главный конкурент"
  },
  {
    "episode": 196,
    "title": "Столкновение слёз! Горячая кровь — битва студента и сенсея!"
  },
  {
    "episode": 197,
    "title": "Сбор одиннадцати из Конохи"
  },
  {
    "episode": 198,
    "title": "АНБУ отступает, воспоминания Наруто"
  },
  {
    "episode": 199,
    "title": "Промах мимо цели"
  },
  {
    "episode": 200,
    "title": "Сильный помощник"
  },
  {
    "episode": 201,
    "title": "Множественные ловушки, обратный отсчёт для разрушения"
  },
  {
    "episode": 202,
    "title": "Спецвыпуск! 5 лучших сражений ниндзя!"
  },
  {
    "episode": 203,
    "title": "Решение Куренаи, команда №8 покинута"
  },
  {
    "episode": 204,
    "title": "Цель - Якумо, запечатанные способности"
  },
  {
    "episode": 205,
    "title": "Сверхсекретная миссия Куренаи, обещание Третьему"
  },
  {
    "episode": 206,
    "title": "Гэндзюцу или реальность? Те кто управляют пятью чувствами"
  },
  {
    "episode": 207,
    "title": "Способности которые должны быть запечатаны"
  },
  {
    "episode": 208,
    "title": "Ценимый по весу артефакт"
  },
  {
    "episode": 209,
    "title": "Цель - Шинобазу"
  },
  {
    "episode": 210,
    "title": "Лес замешательства"
  },
  {
    "episode": 211,
    "title": "Воспоминания пламени"
  },
  {
    "episode": 212,
    "title": "У каждого свой путь"
  },
  {
    "episode": 213,
    "title": "Утраченные воспоминания"
  },
  {
    "episode": 214,
    "title": "Прозрение"
  },
  {
    "episode": 215,
    "title": "Бегство от прошлого"
  },
  {
    "episode": 216,
    "title": "Пропавший ремесленник - преследуемый Шукаку"
  },
  {
    "episode": 217,
    "title": "Союзники Песка - ниндзя Листа"
  },
  {
    "episode": 218,
    "title": "Запечатанный песок - контратака"
  },
  {
    "episode": 219,
    "title": "Возрождение Совершенного Оружия"
  },
  {
    "episode": 220,
    "title": "В путь"
  }
]
